mlguardian/__init__.py
mlguardian/_version.py
mlguardian/config.py
mlguardian/decorators.py
mlguardian/monitored_model.py
mlguardian/telemetry_queue.py
mlguardian/telemetry_sender.py
mlguardian/utils.py
mlguardian-0.1.0.dist-info/licenses/LICENSE
mlguardian-0.1.0.dist-info/METADATA
mlguardian-0.1.0.dist-info/WHEEL
mlguardian-0.1.0.dist-info/top_level.txt
mlguardian-0.1.0.dist-info/RECORD
