Metadata-Version: 2.4
Name: mlguardian
Version: 0.1.0
Summary: MLGuardian Agent SDK - Monitor and send telemetry from your ML models.
Author: Varun Teja Chunduri
License: MIT License
Project-URL: Homepage, https://github.com/varunteja0/mlguardian
Classifier: Programming Language :: Python :: 3
Classifier: License :: OSI Approved :: MIT License
Classifier: Operating System :: OS Independent
Requires-Python: >=3.8
License-File: LICENSE
Requires-Dist: requests>=2.25.0
Dynamic: license-file
